svarog/__init__.py
svarog/checks.py
svarog/compat.py
svarog/dispatchers/__init__.py
svarog/dispatchers/functional.py
svarog/dispatchers/multi.py
svarog/forges.py
svarog/py.typed
svarog/svarog.py
svarog/tools.py
svarog/types.py
svarog-0.3.2.dist-info/LICENSE
svarog-0.3.2.dist-info/METADATA
svarog-0.3.2.dist-info/WHEEL
svarog-0.3.2.dist-info/RECORD
