Metadata-Version: 2.1
Name: svarog
Version: 0.3.2
Summary: Svarog allow to create object from non typed data
Home-page: https://github.com/dswistowski/svarog/
License: MIT
Keywords: svarog,json,structure,typing
Author: Damian Świstowski
Author-email: damian@swistowski.org
Requires-Python: >=3.8,<4.0
Classifier: Development Status :: 2 - Pre-Alpha
Classifier: Intended Audience :: Developers
Classifier: License :: OSI Approved :: MIT License
Classifier: Natural Language :: English
Classifier: Programming Language :: Python :: 3
Classifier: Programming Language :: Python :: 3.8
Classifier: Programming Language :: Python :: 3.9
Classifier: Programming Language :: Python :: 3.10
Classifier: Programming Language :: Python :: 3.11
Project-URL: Repository, https://github.com/dswistowski/svarog/
